ironpipe/__init__.py
ironpipe/api.py
ironpipe/error.py
ironpipe/extension.py
ironpipe/run.py
ironpipe/subscribe.py
ironpipe-1.0.0a23.dist-info/DESCRIPTION.rst
ironpipe-1.0.0a23.dist-info/METADATA
ironpipe-1.0.0a23.dist-info/RECORD
ironpipe-1.0.0a23.dist-info/WHEEL
ironpipe-1.0.0a23.dist-info/metadata.json
ironpipe-1.0.0a23.dist-info/top_level.txt
